scystream/__init__.py
scystream/sdk/__init__.py
scystream/sdk/core.py
scystream/sdk/scheduler.py
scystream/sdk/spark_manager.py
scystream/sdk/config/__init__.py
scystream/sdk/config/compute_block_utils.py
scystream/sdk/config/config_loader.py
scystream/sdk/config/entrypoints.py
scystream/sdk/config/models.py
scystream/sdk/database_handling/__init__.py
scystream/sdk/database_handling/postgres_manager.py
scystream/sdk/env/__init__.py
scystream/sdk/env/settings.py
scystream/sdk/file_handling/__init__.py
scystream/sdk/file_handling/s3_manager.py
scystream/sdk/spark_jars/postgresql-42.7.4.jar
scystream_sdk-1.2.2.dist-info/licenses/LICENSE
scystream_sdk-1.2.2.dist-info/METADATA
scystream_sdk-1.2.2.dist-info/WHEEL
scystream_sdk-1.2.2.dist-info/top_level.txt
scystream_sdk-1.2.2.dist-info/RECORD
