Metadata-Version: 2.4
Name: scystream-sdk
Version: 1.2.2
Summary: The official SDK for developing scystream compute blocks
Home-page: https://github.com/RWTH-TIME/scystream-sdk
Author: Felix Evers, Paul Kalhorn
Author-email: evers@time.rwth-aachen.de, kalhorn@time.rwth-aachen.de
License: MIT
Classifier: Programming Language :: Python :: 3
Classifier: License :: OSI Approved :: MIT License
Classifier: Operating System :: OS Independent
Requires-Python: >=3.6
License-File: LICENSE
Requires-Dist: pydantic>=2.9.2
Requires-Dist: PyYAML>=6.0.2
Requires-Dist: pydantic-settings>=2.6.1
Requires-Dist: pyspark>=3.5.3
Requires-Dist: setuptools>=75.5.0
Requires-Dist: boto3>=1.35.65
Provides-Extra: dev
Requires-Dist: sphinx>=8.1.3; extra == "dev"
Requires-Dist: sphinx-autodoc-typehints>=2.5.0; extra == "dev"
Requires-Dist: sphinxawesome-theme>=5.3.2; extra == "dev"
Requires-Dist: Pygments>=2.18.0; extra == "dev"
Dynamic: author
Dynamic: author-email
Dynamic: classifier
Dynamic: description
Dynamic: description-content-type
Dynamic: home-page
Dynamic: license
Dynamic: license-file
Dynamic: provides-extra
Dynamic: requires-dist
Dynamic: requires-python
Dynamic: summary
